nosemerge.py
setup.cfg
setup.py
nosemerge.egg-info/PKG-INFO
nosemerge.egg-info/SOURCES.txt
nosemerge.egg-info/dependency_links.txt
nosemerge.egg-info/top_level.txt