Metadata-Version: 1.1
Name: nosemerge
Version: 0.1
Summary: Simple nosetests xml report merge tool
Home-page: https://github.com/C-Pro/nosemerge
Author: Sergey Melekhin
Author-email: cpro29a@gmail.com
License: LGPL
Download-URL: https://github.com/C-Pro/nosemerge/tarball/0.1
Keywords: xml unittest nose nosetests
Platform: UNKNOWN
